clients/__init__.py
models/__init__.py
utils/__init__.py
utils/logger.py
utils/timer.py
ar_shared_lib-1.0.0.dist-info/LICENSE
ar_shared_lib-1.0.0.dist-info/METADATA
ar_shared_lib-1.0.0.dist-info/WHEEL
ar_shared_lib-1.0.0.dist-info/top_level.txt
ar_shared_lib-1.0.0.dist-info/RECORD
